golem_cert_companion/__init__.py
golem_cert_companion/binary_manager.py
golem_cert_companion/certificate_manager.py
golem_cert_companion/templates.py
golem_cert_companion-0.2.3.dist-info/LICENSE
golem_cert_companion-0.2.3.dist-info/METADATA
golem_cert_companion-0.2.3.dist-info/WHEEL
golem_cert_companion-0.2.3.dist-info/entry_points.txt
golem_cert_companion-0.2.3.dist-info/top_level.txt
golem_cert_companion-0.2.3.dist-info/RECORD
