Metadata-Version: 2.1
Name: golem-cert-companion
Version: 0.2.3
Summary: Certificate companion for Golem
Author-email: Phillip <phillip@golem.network>
Project-URL: Homepage, https://github.com/golemfactory/golem-cert-companion
Requires-Python: >=3.8
License-File: LICENSE
Requires-Dist: colorama>=0.4.4
Requires-Dist: python-dateutil>=2.8.2
Requires-Dist: requests>=2.28.0
Requires-Dist: pathlib>=1.0.1
